cyberdb/__init__.py
cyberdb/cyberdict.py
cyberdb/cyberlist.py
cyberdb/my_manager.py
cyberdb/mymanager.py
cyberdb/tool.py
cyberdb/data/__init__.py
cyberdb/data/datas.py
cyberdb/extensions/__init__.py
cyberdb/extensions/nonce.py
cyberdb/extensions/signature.py
cyberdb/network/__init__.py
cyberdb/network/aioclient.py
cyberdb/network/client.py
cyberdb/network/route.py
cyberdb/network/server.py
cyberdb_old/__init__.py
cyberdb_old/cyberdict.py
cyberdb_old/cyberlist.py
cyberdb_old/tool.py
CyberDB-0.9.3.dist-info/LICENSE
CyberDB-0.9.3.dist-info/METADATA
CyberDB-0.9.3.dist-info/WHEEL
CyberDB-0.9.3.dist-info/top_level.txt
CyberDB-0.9.3.dist-info/RECORD
