Metadata-Version: 2.1
Name: CyberDB
Version: 0.9.3
Summary: CyberDB is a lightweight Python in-memory database. It is designed to use Python's built-in data structures Dictionaries, Lists for data storage, efficient communication through Socket TCP, and provide data persistence. This module can be used in hard disk database caching, Gunicorn inter-process communication, distributed computing and other fields.
Author: Cyberbolt
Author-email: dtconlyone@gmail.com
Classifier: Programming Language :: Python :: 3
Classifier: License :: OSI Approved :: MIT License
Classifier: Operating System :: OS Independent
License-File: LICENSE
Requires-Dist: APScheduler (>=3.9.1)
Requires-Dist: obj-encrypt (==0.7.0)
